snekify.py
snekify-2.0.1.dist-info/LICENSE
snekify-2.0.1.dist-info/METADATA
snekify-2.0.1.dist-info/WHEEL
snekify-2.0.1.dist-info/entry_points.txt
snekify-2.0.1.dist-info/top_level.txt
snekify-2.0.1.dist-info/RECORD
