Metadata-Version: 2.1
Name: snekify
Version: 2.0.1
Summary: Convert text to snake case
Home-page: https://github.com/tusharsadhwani/snekify
Author: Tushar Sadhwani
Author-email: tushar.sadhwani000@gmail.com
License: UNKNOWN
Platform: UNKNOWN
Classifier: Programming Language :: Python :: 3
Classifier: License :: OSI Approved :: MIT License
Classifier: Operating System :: OS Independent
Requires-Python: >=3.6
Requires-Dist: pytest
